[
  {
    "id": "1",
    "tipoProblema": "Buraco na via",
    "descricao": "Buraco grande atrapalhando o trânsito.",
    "bairro": "Centro",
    "endereco": "Rua das Flores, 123",
    "latitude": -26.899,
    "longitude": -49.231,
    "gravidade": 3,
    "gravidadeIA": 4,
    "status": "ABERTO",
    "secretariaOrigem": "Infraestrutura",
    "dataCriacao": "2025-12-01T10:00:00",
    "dataAtualizacao": "2025-12-02T15:00:00",
    "metadata": { "prioridade": "alta", "fotos": 2 }
  },
  {
    "id": "2",
    "tipoProblema": "Iluminação pública",
    "descricao": "Poste sem luz há mais de uma semana.",
    "bairro": "Centro",
    "endereco": "Av. Brasil, 456",
    "latitude": -26.901,
    "longitude": -49.235,
    "gravidade": 2,
    "gravidadeIA": 2,
    "status": "EM_ANDAMENTO",
    "secretariaOrigem": "Serviços Urbanos",
    "dataCriacao": "2025-12-01T11:30:00",
    "dataAtualizacao": "2025-12-02T16:00:00",
    "metadata": { "prioridade": "média", "fotos": 1 }
  },
  {
    "id": "3",
    "tipoProblema": "Coleta de lixo",
    "descricao": "Lixo acumulado sem coleta há 3 dias.",
    "bairro": "Centro",
    "endereco": "Rua João Paulo II, 789",
    "latitude": -26.905,
    "longitude": -49.240,
    "gravidade": 4,
    "gravidadeIA": 5,
    "status": "FECHADO",
    "secretariaOrigem": "Meio Ambiente",
    "dataCriacao": "2025-12-01T09:00:00",
    "dataAtualizacao": "2025-12-02T14:00:00",
    "metadata": { "prioridade": "alta", "fotos": 0 }
  },
  {
    "id": "4",
    "tipoProblema": "Alagamento",
    "descricao": "Rua alagada após chuva forte.",
    "bairro": "Vila Nova",
    "endereco": "Rua das Palmeiras, 321",
    "latitude": -26.910,
    "longitude": -49.250,
    "gravidade": 5,
    "gravidadeIA": 5,
    "status": "ABERTO",
    "secretariaOrigem": "Defesa Civil",
    "dataCriacao": "2025-12-01T12:00:00",
    "dataAtualizacao": "2025-12-02T18:00:00",
    "metadata": { "prioridade": "alta", "fotos": 3 }
  },
  {
    "id": "5",
    "tipoProblema": "Árvore caída",
    "descricao": "Árvore bloqueando a calçada.",
    "bairro": "Vila Nova",
    "endereco": "Rua das Palmeiras, 400",
    "latitude": -26.911,
    "longitude": -49.251,
    "gravidade": 3,
    "gravidadeIA": 3,
    "status": "EM_ANDAMENTO",
    "secretariaOrigem": "Meio Ambiente",
    "dataCriacao": "2025-12-01T13:00:00",
    "dataAtualizacao": "2025-12-02T19:00:00",
    "metadata": { "prioridade": "média", "fotos": 2 }
  },
  {
    "id": "6",
    "tipoProblema": "Buraco na via",
    "descricao": "Buraco pequeno mas perigoso para motos.",
    "bairro": "Vila Nova",
    "endereco": "Rua das Palmeiras, 450",
    "latitude": -26.912,
    "longitude": -49.252,
    "gravidade": 2,
    "gravidadeIA": 3,
    "status": "ABERTO",
    "secretariaOrigem": "Infraestrutura",
    "dataCriacao": "2025-12-01T14:00:00",
    "dataAtualizacao": "2025-12-02T20:00:00",
    "metadata": { "prioridade": "baixa", "fotos": 1 }
  },
  {
    "id": "7",
    "tipoProblema": "Iluminação pública",
    "descricao": "Vários postes apagados na mesma rua.",
    "bairro": "Rio Morto",
    "endereco": "Rua das Águas, 50",
    "latitude": -26.920,
    "longitude": -49.260,
    "gravidade": 3,
    "gravidadeIA": 4,
    "status": "ABERTO",
    "secretariaOrigem": "Serviços Urbanos",
    "dataCriacao": "2025-12-01T15:00:00",
    "dataAtualizacao": "2025-12-02T21:00:00",
    "metadata": { "prioridade": "alta", "fotos": 4 }
  },
  {
    "id": "8",
    "tipoProblema": "Coleta de lixo",
    "descricao": "Acúmulo de lixo em esquina movimentada.",
    "bairro": "Rio Morto",
    "endereco": "Rua das Águas, 60",
    "latitude": -26.921,
    "longitude": -49.261,
    "gravidade": 4,
    "gravidadeIA": 4,
    "status": "EM_ANDAMENTO",
    "secretariaOrigem": "Meio Ambiente",
    "dataCriacao": "2025-12-01T16:00:00",
    "dataAtualizacao": "2025-12-02T22:00:00",
    "metadata": { "prioridade": "alta", "fotos": 2 }
  }
]
